<?xml version="1.0" encoding="utf-8" ?><dwsync><file name="footer.inc.php" server="91.208.99.4/public_html/" local="3656335478" remote="322440159392910944" Dst="-1" /><file name="head.inc.php" server="91.208.99.4/public_html/" local="3656335437" remote="322440159392910884" Dst="-1" /><file name="products.inc.php" server="limecat.co.uk//public_html/build.fullbhuna.com/" local="3657199573" remote="322299421910422776" Dst="-1" /><file name="header.inc.php" server="limecat.co.uk//public_html/build.fullbhuna.com/" local="3661876303" remote="322299421910422776" Dst="-1" /><file name="cron.inc.php" server="limecat.co.uk//public_html/build.fullbhuna.com/" local="3625728816" remote="322633673440251400" Dst="-1" /><file name="signupheader.inc.php" server="limecat.co.uk//public_html/build.fullbhuna.com/" local="3625728815" remote="322633673440251400" Dst="-1" /><file name="head.inc.php" server="limecat.co.uk//public_html/build.fullbhuna.com/" local="3662196631" remote="322299421910422776" Dst="-1" /><file name="footer.inc.php" server="limecat.co.uk//public_html/build.fullbhuna.com/" local="3661868577" remote="322299421910422776" Dst="-1" /><file name="webBadge.inc.php" server="limecat.co.uk//public_html/build.fullbhuna.com/" local="3636995304" remote="322633673440251400" Dst="-1" /><file name="class.twitter100.php" server="limecat.co.uk//public_html/build.fullbhuna.com/" local="3625728816" remote="322633673440251400" Dst="-1" /><file name="translation.inc.php" server="limecat.co.uk//public_html/build.fullbhuna.com/" local="3625728815" remote="322633673440251400" Dst="-1" /></dwsync>